google-drive-sheets/__init__.py
google-drive-sheets/google_drive.py
google-drive-sheets/util.py
googledrivesheets/__init__.py
googledrivesheets/google_drive.py
googledrivesheets/util.py
google_drive_sheets-0.0.6.dist-info/METADATA
google_drive_sheets-0.0.6.dist-info/WHEEL
google_drive_sheets-0.0.6.dist-info/top_level.txt
google_drive_sheets-0.0.6.dist-info/RECORD
