Metadata-Version: 2.1
Name: google-drive-sheets
Version: 0.0.6
Summary: Utilities for Google Drive and Google Sheets APIs
Home-page: https://github.com/nsp8/google-drive-sheets
Author: Nishant Parmar
Author-email: nish240893@gmail.com
License: UNKNOWN
Keywords: python,google drive,google sheets,gsuite
Platform: UNKNOWN
Classifier: Development Status :: 3 - Alpha
Classifier: Intended Audience :: Developers
Classifier: Programming Language :: Python :: 3
Classifier: Operating System :: Unix
Classifier: Operating System :: MacOS :: MacOS X
Classifier: Operating System :: Microsoft :: Windows
Requires-Python: >=3.6
Requires-Dist: pandas
Requires-Dist: numpy
Requires-Dist: google-api-python-client
Requires-Dist: google-auth-httplib2
Requires-Dist: google-auth-oauthlib
Requires-Dist: requests
Requires-Dist: xlrd
Requires-Dist: openpyxl
Requires-Dist: oauth2client
